{"ts":"2026-07-23T04:55:03+00:00","nse_open":true,"us_open":false,"quotes":[{"sym":"NIFTY 50","label":"Nifty 50","last":23945.9,"chg":-0.21},{"sym":"NIFTY BANK","label":"Bank Nifty","last":56824.65,"chg":-0.53},{"sym":"NIFTY IT","label":"Nifty IT","last":28464.55,"chg":-0.3},{"sym":"NIFTY MIDCAP 100","label":"Midcap 100","last":62141.35,"chg":-0.26},{"sym":"INDIA VIX","label":"India VIX","last":13.1,"chg":-1.42},{"sym":"^GSPC","label":"S&P 500","last":7498.96,"chg":-0.14},{"sym":"^IXIC","label":"Nasdaq","last":25690.9,"chg":-0.57},{"sym":"^RUT","label":"Russell 2k","last":2959.94,"chg":-0.92},{"sym":"DX-Y.NYB","label":"DXY","last":100.97,"chg":-0.12},{"sym":"GC=F","label":"Gold","last":4125.1,"chg":-0.06},{"sym":"SI=F","label":"Silver","last":59.99,"chg":0.13},{"sym":"HG=F","label":"Copper","last":6.53,"chg":0.36},{"sym":"CL=F","label":"WTI","last":88.15,"chg":0.31},{"sym":"BTC-USD","label":"Bitcoin","last":65580.11,"chg":-0.77},{"sym":"INR=X","label":"USD/INR","last":96.53,"chg":-0.03},{"sym":"EURUSD=X","label":"EUR/USD","last":1.14,"chg":0.22},{"sym":"TLT","label":"TLT (20Y+)","last":83.44,"chg":-0.31}]}